refcuckoo.cp310-win_amd64.pyd
refcuckoo-stubs/__init__.pyi
refcuckoo-1.0.dist-info/LICENSE
refcuckoo-1.0.dist-info/METADATA
refcuckoo-1.0.dist-info/WHEEL
refcuckoo-1.0.dist-info/top_level.txt
refcuckoo-1.0.dist-info/RECORD
