Metadata-Version: 2.1
Name: refcuckoo
Version: 1.0
Summary: A cuckoo filter implementation.
Home-page: https://github.com/electrumsv/cuckoofilter
Author: Roger Taylor
Author-email: roger.taylor.email@gmail.com
License: Apache License v2.0
Platform: UNKNOWN
License-File: LICENSE
